{"servers": {"9073": {"image_url": "https://i.imgur.com/OfM7dfT.png", "description": "Fat ezuw 25 dedis of arb.", "channel_id": 1350212388703699035, "message_id": 1355245843598282783}, "9066": {"image_url": ".", "description": "fatezuw dupe shit.", "channel_id": 1350212388703699035, "message_id": 1355245848136646666}, "9325": {"image_url": "https://i.imgur.com/x6c7On0.png", "description": "tribe TM , fat asfk 20+ arb,20+dust, 10+ingots,10+paste,70+hide", "channel_id": 1350212388703699035, "message_id": 1355245858072821911}, "9324": {"image_url": ".", "description": "Rocket Dodos - fat.", "channel_id": 1350212388703699035, "message_id": 1355245862531633245}, "9287": {"image_url": "https://i.imgur.com/4ysuGir.png", "description": "Tribe Juan.    fat sn", "channel_id": 1350212388703699035, "message_id": 1355245866482663585}, "9299": {"image_url": ".", "description": "Tribe Triangle Gang, private giga line can steal ez", "channel_id": 1350212388703699035, "message_id": 1355245870039433277}, "9309": {"image_url": ".", "description": "Tribe no names -fat", "channel_id": 1350212388703699035, "message_id": 1355245874548047872}, "9301": {"image_url": ".", "description": "Tribe CCG - fat", "channel_id": 1350212388703699035, "message_id": 1355245879057191102}, "9308": {"image_url": ".", "description": "can mesh", "channel_id": 1350212388703699035, "message_id": 1355245884362850425}, "9312": {"image_url": ".", "description": "rocket dodos - fat", "channel_id": 1350212388703699035, "message_id": 1355245889584631849}, "9313": {"image_url": "https://i.imgur.com/3Atkq67.png", "description": "Tribe T- small side easy mesh, main hard", "channel_id": 1350212388703699035, "message_id": 1355245900099747910}, "9302": {"image_url": "https://i.imgur.com/2l3FUcq.png", "description": "Tribe Nordeste- main moon pool ez, main artifact crafting, can tek rifle.", "channel_id": 1350212388703699035, "message_id": 1355245903744729199}, "9300": {"image_url": "https://i.imgur.com/ORPBrLf.png", "description": "small side no turrets, water ,  main room 50 turrets can throw tames inside.", "channel_id": 1350212388703699035, "message_id": 1355245907788173463}, "9285": {"image_url": ".", "description": "The saviors", "channel_id": 1350212388703699035, "message_id": 1355245911307194438}, "9298": {"image_url": "https://i.imgur.com/IkjY0Ma.png", "description": "Otter Club - fat", "channel_id": 1350212388703699035, "message_id": 1355245914935005398}, "9292": {"image_url": ".", "description": "Vanguard - fat sn private lines + carcha line", "channel_id": 1350212388703699035, "message_id": 1355245919859114034}, "9246": {"image_url": ".", "description": "gunni server.", "channel_id": 1350212388703699035, "message_id": 1355245925488001207}}}