{"servers": {"9073": {"image_url": "https://i.imgur.com/OfM7dfT.png", "description": "Fat ezuw 25 dedis of arb.", "channel_id": 1350210604186734705, "message_id": 1354222150994755724}, "9066": {"image_url": ".", "description": "fatezuw dupe shit.", "channel_id": 1350210604186734705, "message_id": 1354222153863528622}, "9325": {"image_url": "https://i.imgur.com/x6c7On0.png", "description": "tribe TM , fat asfk 20+ arb,20+dust, 10+ingots,10+paste,70+hide", "channel_id": 1350210604186734705, "message_id": 1354222157382815826}, "9324": {"image_url": ".", "description": "Rocket Dodos - fat.", "channel_id": 1350210604186734705, "message_id": 1354222160909959338}, "9287": {"image_url": "https://i.imgur.com/4ysuGir.png", "description": "Tribe Juan.    fat sn", "channel_id": 1350210604186734705, "message_id": 1354222164319932527}, "9299": {"image_url": ".", "description": "Tribe Triangle Gang, private giga line can steal ez", "channel_id": 1350210604186734705, "message_id": 1354222167557935166}, "9309": {"image_url": ".", "description": "Tribe no names -fat", "channel_id": 1350210604186734705, "message_id": 1354222170624229500}, "9301": {"image_url": ".", "description": "Tribe CCG - fat", "channel_id": 1350210604186734705, "message_id": 1354222174013100173}, "9308": {"image_url": ".", "description": "can mesh", "channel_id": 1350210604186734705, "message_id": 1354222177146372126}, "9312": {"image_url": ".", "description": "rocket dodos - fat", "channel_id": 1350210604186734705, "message_id": 1354222179952365680}, "9313": {"image_url": "https://i.imgur.com/3Atkq67.png", "description": "Tribe T- small side easy mesh, main hard", "channel_id": 1350210604186734705, "message_id": 1354222183362334750}, "9302": {"image_url": "https://i.imgur.com/2l3FUcq.png", "description": "Tribe Nordeste- main moon pool ez, main artifact crafting, can tek rifle.", "channel_id": 1350210604186734705, "message_id": 1354222186738745394}, "9300": {"image_url": "https://i.imgur.com/ORPBrLf.png", "description": "small side no turrets, water ,  main room 50 turrets can throw tames inside.", "channel_id": 1350210604186734705, "message_id": 1354222189796266035}, "9285": {"image_url": ".", "description": "The saviors", "channel_id": 1350210604186734705, "message_id": 1354222193231401002}, "9298": {"image_url": "https://i.imgur.com/IkjY0Ma.png", "description": "Otter Club - fat", "channel_id": 1350210604186734705, "message_id": 1354222198449111091}, "9292": {"image_url": ".", "description": "Vanguard - fat sn private lines + carcha line", "channel_id": 1350210604186734705, "message_id": 1354222202274447480}, "9246": {"image_url": ".", "description": "gunni server.", "channel_id": 1350210604186734705, "message_id": 1354222205818372156}}}