{"servers": {"9073": {"image_url": "https://i.imgur.com/OfM7dfT.png", "description": "Fat ezuw 25 dedis of arb.", "channel_id": 1350212388703699035, "message_id": 1355323697468149781}, "9066": {"image_url": ".", "description": "fatezuw dupe shit.", "channel_id": 1350212388703699035, "message_id": 1355323701046022207}, "9325": {"image_url": "https://i.imgur.com/x6c7On0.png", "description": "tribe TM , fat asfk 20+ arb,20+dust, 10+ingots,10+paste,70+hide", "channel_id": 1350212388703699035, "message_id": 1355323704837538013}, "9324": {"image_url": ".", "description": "Rocket Dodos - fat.", "channel_id": 1350212388703699035, "message_id": 1355323711796019290}, "9287": {"image_url": "https://i.imgur.com/4ysuGir.png", "description": "Tribe Juan.    fat sn", "channel_id": 1350212388703699035, "message_id": 1355323715289747526}, "9299": {"image_url": ".", "description": "Tribe Triangle Gang, private giga line can steal ez", "channel_id": 1350212388703699035, "message_id": 1355323718489866302}, "9309": {"image_url": ".", "description": "Tribe no names -fat", "channel_id": 1350212388703699035, "message_id": 1355323722126463176}, "9301": {"image_url": ".", "description": "Tribe CCG - fat", "channel_id": 1350212388703699035, "message_id": 1355323725356208170}, "9308": {"image_url": ".", "description": "can mesh", "channel_id": 1350212388703699035, "message_id": 1355323729445654660}, "9312": {"image_url": ".", "description": "rocket dodos - fat", "channel_id": 1350212388703699035, "message_id": 1355323732813676624}, "9313": {"image_url": "https://i.imgur.com/3Atkq67.png", "description": "Tribe T- small side easy mesh, main hard", "channel_id": 1350212388703699035, "message_id": 1355323736168988839}, "9302": {"image_url": "https://i.imgur.com/2l3FUcq.png", "description": "Tribe Nordeste- main moon pool ez, main artifact crafting, can tek rifle.", "channel_id": 1350212388703699035, "message_id": 1355323739637678140}, "9300": {"image_url": "https://i.imgur.com/ORPBrLf.png", "description": "small side no turrets, water ,  main room 50 turrets can throw tames inside.", "channel_id": 1350212388703699035, "message_id": 1355323742775021590}, "9285": {"image_url": ".", "description": "The saviors", "channel_id": 1350212388703699035, "message_id": 1355323746872721500}, "9298": {"image_url": "https://i.imgur.com/IkjY0Ma.png", "description": "Otter Club - fat", "channel_id": 1350212388703699035, "message_id": 1355323753760030913}, "9292": {"image_url": ".", "description": "Vanguard - fat sn private lines + carcha line", "channel_id": 1350212388703699035, "message_id": 1355323757211943022}, "9246": {"image_url": ".", "description": "gunni server.", "channel_id": 1350212388703699035, "message_id": 1355323761208852584}}}